truthscore/__init__.py
truthscore/config.py
truthscore/consistency.py
truthscore/coverage.py
truthscore/nli.py
truthscore/retrieve.py
truthscore/score.py
truthscore_llm-0.1.4.dist-info/licenses/LICENSE
truthscore_llm-0.1.4.dist-info/METADATA
truthscore_llm-0.1.4.dist-info/WHEEL
truthscore_llm-0.1.4.dist-info/top_level.txt
truthscore_llm-0.1.4.dist-info/RECORD
