Metadata-Version: 2.4
Name: truthscore-llm
Version: 0.1.4
Summary: A research library for evaluating truthfulness of LLM outputs based on evidence agreement, self-consistency, and retrieval coverage
Author: TruthScore Contributors
Project-URL: Homepage, https://github.com/mmsa/truthscore-llm
Project-URL: Documentation, https://github.com/mmsa/truthscore-llm#readme
Project-URL: Repository, https://github.com/mmsa/truthscore-llm
Project-URL: Issues, https://github.com/mmsa/truthscore-llm/issues
Keywords: llm,truth,evaluation,evidence,consistency,research
Classifier: Development Status :: 3 - Alpha
Classifier: Intended Audience :: Science/Research
Classifier: Programming Language :: Python :: 3
Classifier: Programming Language :: Python :: 3.8
Classifier: Programming Language :: Python :: 3.9
Classifier: Programming Language :: Python :: 3.10
Classifier: Programming Language :: Python :: 3.11
Classifier: Topic :: Scientific/Engineering :: Artificial Intelligence
Requires-Python: >=3.8
License-File: LICENSE
Provides-Extra: dev
Requires-Dist: pytest>=7.0; extra == "dev"
Requires-Dist: pytest-cov>=4.0; extra == "dev"
Provides-Extra: nli
Requires-Dist: transformers>=4.0.0; extra == "nli"
Requires-Dist: torch>=1.9.0; extra == "nli"
Dynamic: license-file
